LICENSE
MANIFEST.in
README.md
TracyWidom.py
setup.py
TracyWidom.egg-info/PKG-INFO
TracyWidom.egg-info/SOURCES.txt
TracyWidom.egg-info/dependency_links.txt
TracyWidom.egg-info/requires.txt
TracyWidom.egg-info/top_level.txt